asyncio_throttler/__init__.py
asyncio_throttler/throttle.py
asyncio_throttler-0.1.0.dist-info/DESCRIPTION.rst
asyncio_throttler-0.1.0.dist-info/METADATA
asyncio_throttler-0.1.0.dist-info/RECORD
asyncio_throttler-0.1.0.dist-info/WHEEL
asyncio_throttler-0.1.0.dist-info/metadata.json
asyncio_throttler-0.1.0.dist-info/top_level.txt
