Metadata-Version: 2.0
Name: asyncio-throttler
Version: 0.1.0
Summary: Throttling tools for py3.5+ asyncio.
Home-page: https://github.com/scopely/asyncio_throttler
Author: Anthony Grimes
Author-email: anthony@scopely.com
License: MIT
Platform: UNKNOWN
Classifier: Development Status :: 3 - Alpha
Classifier: Natural Language :: English
Classifier: Programming Language :: Python :: 3.5
